RedLionfishDeconv/RLDeconv3DReiknaOCL.py
RedLionfishDeconv/RLDeconv3DScipy.py
RedLionfishDeconv/RLDeconvolve.py
RedLionfishDeconv/__init__.py
RedLionfishDeconv/helperfunctions.py
RedLionfishDeconv/napari_plugin.py
RedLionfish-0.10.dist-info/LICENSE
RedLionfish-0.10.dist-info/METADATA
RedLionfish-0.10.dist-info/WHEEL
RedLionfish-0.10.dist-info/entry_points.txt
RedLionfish-0.10.dist-info/top_level.txt
RedLionfish-0.10.dist-info/RECORD
